dlt2json/__init__.py
dlt2json-0.0.3.dist-info/LICENSE.txt
dlt2json-0.0.3.dist-info/METADATA
dlt2json-0.0.3.dist-info/WHEEL
dlt2json-0.0.3.dist-info/entry_points.txt
dlt2json-0.0.3.dist-info/top_level.txt
dlt2json-0.0.3.dist-info/RECORD
