Metadata-Version: 2.1
Name: dlt2json
Version: 0.0.3
Summary: convert a dlt file to json
Home-page: https://github.com/r2b1d1/dlt2json
Author: Riadh Abidi
Author-email: riadh.abidi@outlook.com
License: UNKNOWN
Platform: UNKNOWN
Classifier: Development Status :: 2 - Pre-Alpha
Classifier: License :: OSI Approved :: MIT License
Classifier: Programming Language :: Python :: 3
Requires-Python: >=3.6
Requires-Dist: logzero
